MANIFEST.in
requirements.txt
setup.cfg
setup.py
doc/AWS_installation.rst
doc/ChIPseq_modules_HOMER.rst
doc/ChIPseq_modules_MACS.rst
doc/Makefile
doc/RNAseq_Tuxedo_Modules.rst
doc/RNAseq_cancer_modules.rst
doc/RNAseq_cancer_modules_TCGA.rst
doc/RNAseq_counts_modules.rst
doc/RNAseq_counts_modules_TCGA.rst
doc/WGS_WES_modules.rst
doc/about.rst
doc/adding_modules.rst
doc/all_modules.rst
doc/conf.py
doc/contents.rst
doc/copyright.rst
doc/custom_pipelines.rst
doc/databases.rst
doc/dependencies.rst
doc/history.rst
doc/index.rst
doc/installation.rst
doc/make.bat
doc/miRNAseq_Tuxedo_Modules.rst
doc/miRNAseq_counts_modules.rst
doc/mutect_modules.rst
doc/parameter_file.rst
doc/pipelines.rst
doc/requirements.txt
doc/resources.rst
doc/tutorial.rst
doc/omics_pipebuild/doctrees/AWS_installation.doctree
doc/omics_pipebuild/doctrees/ChIPseq_modules_HOMER.doctree
doc/omics_pipebuild/doctrees/ChIPseq_modules_MACS.doctree
doc/omics_pipebuild/doctrees/RNAseq_Tuxedo_Modules.doctree
doc/omics_pipebuild/doctrees/RNAseq_cancer_modules.doctree
doc/omics_pipebuild/doctrees/RNAseq_cancer_modules_TCGA.doctree
doc/omics_pipebuild/doctrees/RNAseq_counts_modules.doctree
doc/omics_pipebuild/doctrees/RNAseq_counts_modules_TCGA.doctree
doc/omics_pipebuild/doctrees/WGS_WES_modules.doctree
doc/omics_pipebuild/doctrees/about.doctree
doc/omics_pipebuild/doctrees/adding_modules.doctree
doc/omics_pipebuild/doctrees/all_modules.doctree
doc/omics_pipebuild/doctrees/contents.doctree
doc/omics_pipebuild/doctrees/copyright.doctree
doc/omics_pipebuild/doctrees/custom_pipelines.doctree
doc/omics_pipebuild/doctrees/databases.doctree
doc/omics_pipebuild/doctrees/dependencies.doctree
doc/omics_pipebuild/doctrees/environment.pickle
doc/omics_pipebuild/doctrees/history.doctree
doc/omics_pipebuild/doctrees/index.doctree
doc/omics_pipebuild/doctrees/installation.doctree
doc/omics_pipebuild/doctrees/miRNAseq_Tuxedo_Modules.doctree
doc/omics_pipebuild/doctrees/miRNAseq_counts_modules.doctree
omics_pipe.egg-info/PKG-INFO
omics_pipe.egg-info/SOURCES.txt
omics_pipe.egg-info/dependency_links.txt
omics_pipe.egg-info/entry_points.txt
omics_pipe.egg-info/requires.txt
omics_pipe.egg-info/top_level.txt
