Metadata-Version: 1.0
Name: omics-pipe
Version: 1.1.3
Summary: Extensible computational pipeline for running next generation sequencing analyses
Home-page: https://bitbucket.org/sulab/omics_pipe
Author: Kathleen Fisch, Ph.D.
Author-email: kfisch@scripps.edu
License: MIT
Download-URL: http://pypi.python.org/pypi/omics_pipe
Keywords: biology omics transcriptomics pipeline RNA-seq ChIP-seq WGS WES genome exome HPC
Platform: UNKNOWN
Classifier: Programming Language :: Python
Classifier: Development Status :: 4 - Beta
Classifier: License :: OSI Approved :: MIT License
Classifier: Operating System :: POSIX
Classifier: Operating System :: MacOS :: MacOS X
Classifier: Operating System :: Microsoft :: Windows
Classifier: Intended Audience :: Science/Research
Classifier: Topic :: Scientific/Engineering :: Bio-Informatics
